Metadata-Version: 2.1
Name: cytominer-eval
Version: 0.1
Summary: Methods to evaluate profiling dataframes with features and metadata
Home-page: https://github.com/cytomining/cytominer-eval
Author: Gregory Way
Author-email: gregory.way@gmail.com
License: BSD 3-Clause License
Platform: UNKNOWN
Requires-Python: >=3.5
